<item xmlns:itunes="http://www.itunes.com/dtds/podcast-1.0.dtd" version="2.0" encoding="UTF-8">
  <title>133《沉默的教室》同学你过来，老师今天请你喝茶</title>
  <link>https://anchor.fm/fanpaifilm/episodes/133-eq7355</link>
  <itunes:image href="https://d3t3ozftmdmh3i.cloudfront.net/production/podcast_uploaded_nologo/12366236/12366236-1611985055171-24c9360bf23d6.jpg"/>
  <description>主播打分：
鲁韵子（资深媒体人）：7分；
“这是一部平庸的好片：导演成功的把一个社会装进了一间教室，但过于黑化的反派和过于狗血的情节，让电影的上限非常明显。”
法兰西胶片（资深媒体人；《碟中谍6》等14期嘉宾；豆瓣微博“法兰西胶片”）：7分；
“单就导演能力而言，本片导演甚至不如《药神》的文牧野。三角恋的设置让影片的一切情感层面的输出都瞬间失效。”
波米：6.5分；“电影中的教室是冷战的沙盘。空间上，美苏的意识形态在此对抗；时间上，纳粹原罪在战后一代的德国青年身上生根。”
《沉默的教室》平均分：6.8分
本期节目流程与目录：
开场曲目：《老师你好》（阴三儿）；
1分5秒-第2分钟：嘉宾信息介绍；
第2分钟-第5分半：影片信息介绍（无剧透）；
第5分半-第9分半：三位主播综合优缺点为影片打分（无剧透）；
第9分半-1小时5分钟：嘉宾“法兰西胶片”、“鲁韵子”和波米先谈《沉默的教室》“优点” （涉及剧透）：
1、嘉宾“法兰西胶片”认为影片完成度很高，最后泰奥一家的分离段落让人印象深刻；
2、嘉宾“鲁韵子”觉得影片知识分子气息浓厚，以小见大的目的和成果都很清晰，“死亡诗社”段落虽然老套但仍然让人触动；
3、波米觉得电影剧作水平很高，以统一母题动作带领全片；官二代与父亲离别段落非常出色；
1小时5分钟-1小时44分半：交换意见，三位主播谈影片缺点（涉及剧透）：
1、胶片觉得影片主题先行，很多地方太过算计、功能性太强；照片和三角恋的情节有些失真；
2、鲁韵子觉得电影匠气太重，反派设定过于妖魔化；
3、波米觉得影片结尾处理得相对草率，最大问题是导演层面过于平庸，“悼念”段落的调度太过传统；
三位主播也围绕着该片关于“纳粹”和“德国民族主义”的政治立场问题展开讨论：该片是否存在对“纳粹”问题的暧昧展现？
1小时44分半-尾声：外延环节（涉及剧透）：
1、相关德语电影推荐：重点提及《再见列宁》、《窃听风暴》和《浪潮》，同时谈及新片《冒牌上尉》；
2、重点围绕《审判》、《国家反抗者弗里茨·鲍尔》和《为时不远》简述导演前作；
尾声曲目：《一万个名字》（吴吞）；
影片《沉默的教室》(Das schweigende Klassenzimmer)重要信息：
本片德国分级：FSK-12（对应北美约为PG-13级）；
本期节目重点提及的电影片单：
《审判》（1962）
《毕业生》（1967）
《红圈》（1970）
《末代皇帝》（1987）
《死亡诗社》（1989）
《尤利西斯的凝视》（1995）
《海滩》（2000）
《再见列宁》（2003）
《放牛班的春天》（2004）
《僵尸肖恩》（2004）
《V字仇杀队》（2005）
《窃听风暴》（2006）
《请为我投票》（2007）
《浪潮》（2008）
《无耻混蛋》（2009）
《为时不远》（2010）
《辩护人》（2013）
《国家反抗者弗里茨·鲍尔》（2015）
《希特勒回来了》（2015）
《斯坦福监狱实验》（2015）
《不朽的时光》（2016）
《冒牌上尉》（2017）
《青禾男高》（2017）
《我不是药神》（2018）
</description>
  <pubDate>Mon, 05 Nov 2018 11:00:00 GMT</pubDate>
  <enclosure url="https://anchor.fm/s/4a4df770/podcast/play/26495589/https%3A%2F%2Fd3ctxlq1ktw2nl.cloudfront.net%2Fstaging%2F2021-1-9%2Fc821836f-7d79-bfbd-c7c8-c22e2cf54618.mp3" type="audio/mpeg"/>
  <itunes:duration>2:30:04</itunes:duration>
</item>
