<item xmlns:itunes="http://www.itunes.com/dtds/podcast-1.0.dtd" version="2.0" encoding="UTF-8">
  <title>ma081 响指之后，何去何从？</title>
  <link>https://anchor.fm/fanpaifilm/episodes/ma081-e1ug5q2</link>
  <itunes:image href="https://d3t3ozftmdmh3i.cloudfront.net/production/podcast_uploaded_nologo/12366236/12366236-1611985055171-24c9360bf23d6.jpg"/>
  <description>本期主创团队音频主播：
杨超（国戏教师；《长江图》导演，《野梨树》等10期嘉宾）
法兰西胶片（资深媒体人；《我们》等17期嘉宾，公众号“第一导演”）
编辑排版：效愚；封图设计：画电影moviesketching；
事件简述：
2019年上半年内地电影市场总票房同比缩水近9亿元，观影人次同比减少近1亿。据电影专资办数据，2019年上半年总票房为311.7亿元，同比减少2.7%；总人次为8.08亿，同比减少10.3%；国产影片票房为157.54亿元，同比减少16.94%。而上半年票房过亿的影片共计42部，其中国产影片17部，进口影片25部。
同比2018年上半年，今年2月、4月、6月三个月份票房实现增长，1月、3月、5月票房出现下滑。
开场曲：Into The Future(Murray Gold)
结束曲：《你不要担心》（全仁权）
2019年上半年内地院线票房榜
1、《流浪地球》：46.56亿
2、《复仇者联盟4：终局之战》：42.38亿
3、《疯狂的外星人》：22.02亿
4、《飞驰人生》：17.16亿
5、《大黄蜂》：11.47亿
6、《惊奇队长》：10.33亿
7、《比悲伤更悲伤的故事》：9.53亿
8、《哥斯拉2：怪兽之王》：9.26亿
9、《阿丽塔：战斗天使》：8.95亿
10、《反贪风暴4》：7.95亿
</description>
  <pubDate>Thu, 04 Jul 2019 13:32:22 GMT</pubDate>
  <enclosure url="https://anchor.fm/s/4a4df770/podcast/play/64541954/https%3A%2F%2Fd3ctxlq1ktw2nl.cloudfront.net%2Fstaging%2F2023-1-5%2Feae7dc2e-c835-1c6b-a339-f7441c48296f.mp3" type="audio/mpeg"/>
  <itunes:duration>0:29:55</itunes:duration>
</item>
