<item xmlns:itunes="http://www.itunes.com/dtds/podcast-1.0.dtd" xmlns:content="http://purl.org/rss/1.0/modules/content/">
  <title>ma101 09年，同一件事，百位影人支持波兰斯基</title>
  <link>https://mp.weixin.qq.com/s/kuhgIFkdsQRi-f1Kw-PYOQ</link>
  <itunes:image href="https://d3t3ozftmdmh3i.cloudfront.net/production/podcast_uploaded_nologo/12366236/12366236-1611985055171-24c9360bf23d6.jpg"/>
  <description>
<![CDATA[本期主创团队：
排版：效愚；后期：波米；封图制作：画电影；可关注B站“画电影”频道。
事件简述：
2月28日，第45届凯撒奖举办颁奖典礼，犹太裔导演罗曼·波兰斯基凭《我控诉》获最佳导演奖，《燃烧女子的肖像》导演瑟琳·席安玛与主演阿黛拉·哈内尔当即退场表示抗议，另有几位女性电影人退场。波兰斯基以及《我控诉》的其他所有主创均未出席颁奖典礼。
《我控诉》获本届凯撒奖含导演、男主角、男配角、改编剧本在内12项提名领跑名单。名单公布后，法国电影艺术与科学院面临投票机构内部及学院内部性别组成失衡、多样性透明度缺乏的指控，此后，含演员蕾雅·赛杜、制片人萨义德·本·萨义德在内的超400位法国电影人通过《世界报》发表公开信，呼吁对该组织进行彻底改革，部分法国民众在颁奖礼举办地普雷耶音乐厅外示威。
波兰女导演阿格涅丝卡·霍兰则力挺波兰斯基，表示曾接受并向波兰斯基授奖的美国及法国电影学院因社会情绪变化态度突转，批评电影行业在对待波兰斯基的问题上“表现虚伪”。
值得注意的是，《我控诉》于去年入围76届威尼斯电影节主竞赛单元，时任评委会主席、女导演卢奎西亚·马特尔表示，她将拒绝出席《我控诉》晚宴，也不会为他起立鼓掌。不过她并没有质疑影片出现在电影节上，也支持电影节艺术总监的选片理念，本片最终获评委会大奖与费比西奖（国际影评人联盟奖） 最佳影片奖。
在《我控诉》资源尚未发布情况下，部分豆瓣用户在该影片词条下打一星，截至推送前，本片豆瓣评分降至6.1分，为波兰斯基导演作品最低。
开场曲：North Korea Children Playing the Guitar
结束曲：Making A Murderer)(Gustavo Santaolalla)]]>
  </description>
  <pubDate>Wed, 04 Mar 2020 13:58:56 CST</pubDate>
  <enclosure url="https://anchor.fm/s/4a4df770/podcast/play/64542835/https%3A%2F%2Fd3ctxlq1ktw2nl.cloudfront.net%2Fstaging%2F2023-1-5%2Fbdb0df2c-bbeb-913d-e9b4-3ba8df315a99.mp3" type="audio/mpeg"/>
  <itunes:duration>0:32:26</itunes:duration>
</item>