<item xmlns:itunes="http://www.itunes.com/dtds/podcast-1.0.dtd" xmlns:content="http://purl.org/rss/1.0/modules/content/" version="2.0" encoding="UTF-8">
  <title>《蜘蛛侠：纵横宇宙》伪困境+伪悬念+伪设定=伪神作</title>
  <link>https://podcasters.spotify.com/pod/show/fanpaifilm/episodes/ep-e25iack</link>
  <itunes:image href="https://d3t3ozftmdmh3i.cloudfront.net/production/podcast_uploaded_nologo/12366236/12366236-1611985055171-24c9360bf23d6.jpg"/>
  <description>
<![CDATA[主播打分：
荡科长：5分
《犹大与黑弥赛亚》等20期嘉宾，微博@荡科长，B站视频号“荡科长”
如果这片能有9分，那速激10至少值个8分，又臭又长的动作戏，大家长在派对上用西班牙语说着伐木累，团队内讧反转，超长“下回分解”，有啥区别吗？
法兰西胶片：4分
《黑寡妇》等29期嘉宾，公号“第一导演”
不酷，不有趣，不懂情感表达，不统一，不电影。像脱轨后还在飞速滑行的火车，像饿鬼第一次看到钱。
波米：7分
格温宇宙的画风就像是匹配失败的“杜比视界”文件在低端显示屏的播放效果，人脸一会儿蓝一会儿绿。结合上迈尔斯宇宙从来都是裸眼看（分色）3D的样子，它告诉我们：就算电影的技术实验搞砸了，也可以在这里被回收为一种风格——就像开头达·芬奇秃鹫砸烂的那些艺术品。
节目流程
节目总时长：01:05:30；
1）影片信息介绍；
2）主播为影片打分并阐述理由；
缺点环节涉及如下话题（含剧透）：
1）伪酷炫？情感梗雷同“家人侠”伐木累？
2）伪冤案？蜥蜴帕克难道不是格温杀的？
3）伪倒叙？双重闪回造成人设反跳？
4）伪反派？斑点技能撞脸《奇异博士》？
5）伪笑点？全程十万个冷笑话？
6）伪首领？战力菜鸡的2099如何服众？
7）伪困境？前作艾伦已经是“织网事件”？
8）伪结局？花钱看了个大预告片？
9）伪打戏？文武戏重叠导致信息过载？
10）伪多元？父母絮叨一元拍一遍？
11）伪音效？好莱坞特大混音事故？
以上优点环节涉及如下话题（含剧透）：
1）二刷比一刷观感更好？
2）迈尔斯仍然忠于前作人设？
3）“反大家长制”是潜在主题？
4）“育婴支线”如何成为片中调味剂？
5）如何将“电车困境”多元宇宙化？
6）不同宇宙的画风如何差异化展现？
7）大闹纽瓦约是反“白男中心主义”？
8）对比《银护3》高下立判？
外延涉及如下话题：
1）回顾前作《平行宇宙》作何评价？
2）真人与动画同框对戏是否有可能性？
开场曲：Guggenheim Assemble(Daniel Pemberton)；
结束曲：Across the Spider-Verse (Intro)(Daniel Pemberton)；
影片《蜘蛛侠：纵横宇宙》重要信息：
本片北美分级：PG级；
影片英文原名：Spider-Man: Across the Spider-Verse；
音频后期协助：出雲；
本期片目
《星球大战5：帝国反击战》（1979）
《电子世界争霸战》（1982）
《银翼杀手》（1982）
《席德与南茜》（1986）
《谁陷害了兔子罗杰》（1988）
《空中大灌篮》（1996）
《蜘蛛侠1-2》（2002-2004）
《绿巨人》（2003）
《一代宗师》（2013）
《奇异博士1》（2016）
《美国队长3：内战》（2016）
《乐高蝙蝠侠大电影》（2017）
《每分钟120击》（2017）
《蜘蛛侠1：英雄归来》（2017）
《游侠索罗：星球大战外传》（2018）
《超人总动员2》（2018）
《毒液1-2》（2018-2021）
《蜘蛛侠：平行宇宙》（2018）
《神探蒲松龄》（2019）
《蜘蛛侠3：英雄无归》（2021）
《瞬息全宇宙》（2022）
《雷神4：爱与雷霆》（2022）
《阿凡达2：水之道》（2022）
《超级马力欧兄弟大电影》（2023）
《银河护卫队3》（2023）
《小美人鱼》（2023）
《蜘蛛侠：超越宇宙》（2024）
《复仇者联盟5：康之王朝》（2025）]]>
  </description>
  <pubDate>Sat, 10 Jun 2023 13:01:39 GMT</pubDate>
  <enclosure url="https://anchor.fm/s/4a4df770/podcast/play/71952212/https%3A%2F%2Fd3ctxlq1ktw2nl.cloudfront.net%2Fstaging%2F2023-5-11%2Fcd569c17-799a-d98e-2cea-627b0553e7e3.mp3" type="audio/mpeg"/>
  <itunes:duration>1:05:13</itunes:duration>
</item>