<item xmlns:atom="http://www.w3.org/2005/Atom" xmlns:content="http://purl.org/rss/1.0/modules/content/" xmlns:itunes="http://www.itunes.com/dtds/podcast-1.0.dtd">
  <title>er015《七月与安生》定向推荐。</title>
  <link>https://mp.weixin.qq.com/s/BD4t2ndcYKaTP2M3xkxupg</link>
  <itunes:image href="https://d3t3ozftmdmh3i.cloudfront.net/production/podcast_uploaded_nologo/12366236/12366236-1611985055171-24c9360bf23d6.jpg"/>
  <description>
<![CDATA[影片《七月与安生》重要信息：
导演: 曾国祥
监制：陈可辛
编剧: 林咏琛/李媛/许伊萌/吴楠/安妮宝贝
主演: 周冬雨 /马思纯/李程彬
制片国家/地区: 中国大陆/香港
片长: 109分钟
内地上映日期：2016-09-14
内地是否有2D版：有；]]>
  </description>
  <pubDate>Wed, 14 September 2016 17:00:00 CST</pubDate>
  <enclosure url="https://res.wx.qq.com/voice/getvoice?mediaid=MzIxMTMzNTc5OF8yMjQ3NDg0NDMz" type="audio/mpeg"/>
  <itunes:duration>01:00</itunes:duration>
</item>