<item xmlns:atom="http://www.w3.org/2005/Atom" xmlns:content="http://purl.org/rss/1.0/modules/content/" xmlns:itunes="http://www.itunes.com/dtds/podcast-1.0.dtd">
  <title>er126《伯德小姐》这么一个矫揉造作的小品，有什么资格和诺兰陀螺平起平坐？</title>
  <link>https://mp.weixin.qq.com/s/8vL8Z24e3PiYV1qGYPkPWw</link>
  <itunes:image href="https://d3t3ozftmdmh3i.cloudfront.net/production/podcast_uploaded_nologo/12366236/12366236-1611985055171-24c9360bf23d6.jpg"/>
  <description>

<![CDATA[主播打分与简评：
波米：6分；
小猱：5分；（《玉子》等2期嘉宾，其它打分：《缝纫机乐队》8分；《奇迹男孩》6分；《皮绳上的魂》6分；微博&豆瓣ID“猱困困”）
田野：5分；（《玉子》等6期嘉宾，其它打分：《看不见的客人》7.5分；《羞羞的铁拳》7分；《军舰岛》6分；豆瓣ID“低端的雪盲”）
过往嘉宾对此片打分：
雷普利：7分（《请以你的名字呼唤我》等24期嘉宾，其它打分：《请以》7分；《二代妖精》6分；《解忧杂货店》5分）
短评：“小格局，非极端人设，质地丰富，情感落点精准。抛开国产青春片的衬托，本片最让我喜欢的是她回望中二期的姿态：全然地自我接纳，然后自嘲、自省。”
法兰西胶片：7分；（《灾难艺术家》等10期嘉宾，其它打分：《马戏之王》6.5分；《南极之恋》6分；《奇迹男孩》6分；微博&豆瓣ID“法兰西胶片”）
短评：“胜在娴熟、清醒，少走了很多弯路。但她不是真正的自由，它反而是最商业的。”
荡科长：6.5分；（《底特律》等5期嘉宾，其它打分：《忌日快乐》5分；《妖猫传》5分；《前任3》4分；微博“荡科长”）
短评：“确实是好角色，但性格和情绪都太精准了，像是带着功利心的编排，和青春本身应该具有的躁动和不确定性是矛盾的，所以虽然主角叛逆，但影片整体感觉其实非常保守，给人思考的空间很浅。”
思源：6分（《水形物语》嘉宾，其它打分：《水形物语》7分）
短评：“青春期对于原生家庭的反叛是世界相通的，但是伯德小姐的解决方式却是十分美国本土的。在中国小镇长大的我实在没有办法对于在主角在美国小镇的青春有什么共鸣。然后，果然是哪个学校都嫌弃的，最后只能来NYU了……”（一个来自NYU学生的吐槽——编者注）
海老鼠：6分；（《王牌特工2》等12期嘉宾，其它打分：《奇迹男孩》8分；《至爱梵高》8分；《王牌特工2》5.5分；公众号“seamouse”）
短评：“渴望飞出萨克拉门托的bird，渴望闪光的‘少女时代’。可与同样琐碎记录成长的《少年时代》相比，一个毕业学期，少了时间在发育和青春凿刻的力度，也就少了很多让人同呼吸共命运的乐趣吧？”
蜉蝣：5分；（《请以你的名字呼唤我》等5期嘉宾，其它打分：《马戏之王》6.5分；《南极之恋》6分；《忌日快乐》5分；公众号“不散”）
短评：“缺乏思想和独特魅力的小清新泛滥。”
影片《伯德小姐》(Lady Bird)重要信息：
本片北美分级：R级；
片尾是否有彩蛋：无；
资源状况：1080P网络高清熟肉资源已出；]]>    
  
  </description>
  <pubDate>Tue, 13 February 2018 17:00:00 +0800</pubDate>
  <enclosure url="https://res.wx.qq.com/voice/getvoice?mediaid=MzIxMTMzNTc5OF8yMjQ3NDg3Njk1" type="audio/mpeg"/>
  <itunes:duration>05:30</itunes:duration>
</item>