<item xmlns:atom="http://www.w3.org/2005/Atom" xmlns:content="http://purl.org/rss/1.0/modules/content/" xmlns:itunes="http://www.itunes.com/dtds/podcast-1.0.dtd">
  <title>er227《X战警：黑凤凰》毫无悬念！反派最低评分电影诞生！</title>
  <link>https://mp.weixin.qq.com/s/vkEUqj9bvTUcsIEpK_crRg</link>
  <itunes:image href="https://d3t3ozftmdmh3i.cloudfront.net/production/podcast_uploaded_nologo/12366236/12366236-1611985055171-24c9360bf23d6.jpg"/>
  <description>

<![CDATA[飞行主播-荡科长：4分
往期嘉宾打分及短评：
蜉蝣：5分；（《谁先爱上他的》等10期嘉宾，其它打分：《阿拉丁》7分；《雷霆沙赞！》5分；《小飞象》5分）
短评：开启疯狂毁人设毁剧情模式，所有角色都一脸懵逼不知道自己在干嘛但还要硬着头皮演完的神情，谁戏份少谁就是赚到。终极对决分分钟笑出声。以为多下盘棋就能骗到粉丝的编剧，也别指望能给这个系列善终了。
靳锦：4.5分；（《柔情史》等7期嘉宾，其它打分：《过昭关》7分；《柔情史》5.5分；《徒手攀岩》6.5分）
短评：尽显超英电影的疲态。一个原本讨论少数群体议题的电影，变成了展现少数群体杂耍技能的电影。
法兰西胶片：4分；（《我们》等17期嘉宾，其它打分：《哆啦A梦大雄的月球探险记》7分；《我们》5分；《阿拉丁》5分；微博@法兰西胶片）
短评：这就是公司被收购前从上到下里里外外每个员工都很消极怠工的结果，最聪明的是大表姐，早早地退出了化妆表演界，就这女权台词水准每天八瓶蓝药水不值得。高潮大战还是有水准的，补完了当年《X战警1》列车没开起来就打完了的遗憾。
秦婉：4分；（《风中有朵雨做的云》等10期嘉宾，其它打分：《过昭关》7.5分；《海蒂和爷爷》6.5分；《一条狗的使命2》5分；公号“小婉电影酱”）
短评：一种走流程想快点完结的随意感，结尾火车动作戏尚有些可看性。教授在这一集中更加像个“汤达人”，黑凤凰的能力展现也并无新意。
影片《X战警：黑凤凰》重要信息：
本片北美分级：PG-13级；
是否有国配版：有，本片为上译厂配音；
是否有2D版：无，本片为全球发行的后期转制3D；
片尾是否有彩蛋：无；
内地版是否有删减：无；
是否有IMAX版：有；
IMAX版是否有特殊画幅：无；
是否有全景声版(Dolby Atmos)：有；封图设计：画电影moviesketching]]>    
  
  </description>
  <pubDate>Sun, 09 June 2019 17:00:00 +0800</pubDate>
  <enclosure url="https://res.wx.qq.com/voice/getvoice?mediaid=MzIxMTMzNTc5OF8yMjQ3NDkwNjM0" type="audio/mpeg"/>
  <itunes:duration>03:53</itunes:duration>
</item>